basic_api_client_python/API.py
basic_api_client_python/__init__.py
basic_api_client_python/response.py
basic_api_client_python/tools/__init__.py
basic_api_client_python/tools/account.py
basic_api_client_python/tools/device.py
basic_api_client_python/tools/groups.py
basic_api_client_python/tools/journals.py
basic_api_client_python/tools/marking.py
basic_api_client_python/tools/queues.py
basic_api_client_python/tools/receiving.py
basic_api_client_python/tools/sending.py
basic_api_client_python/tools/serviceMethods.py
basic_api_client_python/tools/webhooks.py
basic_api_client_python-0.0.34.dist-info/LICENSE
basic_api_client_python-0.0.34.dist-info/METADATA
basic_api_client_python-0.0.34.dist-info/WHEEL
basic_api_client_python-0.0.34.dist-info/top_level.txt
basic_api_client_python-0.0.34.dist-info/RECORD
