Metadata-Version: 2.1
Name: basic-api-client-python
Version: 0.0.34
Summary: This library helps you easily create a python '        'application to connect the WhatsApp API using service api.basis-api.com
Home-page: https://github.com/Yard-Team/basic-api-client-python
Author: Ivan Sadovy
Author-email: sadiv@bk.ru
Classifier: Programming Language :: Python :: 3
Classifier: License :: OSI Approved :: MIT License
Classifier: Operating System :: OS Independent
Requires-Python: >=3.5
License-File: LICENSE
Requires-Dist: requests
